oneroster_api/__init__.py
oneroster_api/academic_sessions.py
oneroster_api/base_api.py
oneroster_api/classes.py
oneroster_api/client.py
oneroster_api/courses.py
oneroster_api/demographics.py
oneroster_api/enrollments.py
oneroster_api/users.py
oneroster_api-0.1.7.dist-info/WHEEL
oneroster_api-0.1.7.dist-info/entry_points.txt
oneroster_api-0.1.7.dist-info/METADATA
oneroster_api-0.1.7.dist-info/RECORD
