Metadata-Version: 2.3
Name: oneroster-api
Version: 0.1.7
Summary: Package takes your OneRoster credentials and performs api calls, Library is still a WIP
Author: jvansant13
Author-email: jvansant13 <jermey.vansant@davinciacademy.org>
Requires-Dist: pydantic>=2.11.7
Requires-Dist: requests>=2.32.5
Requires-Python: >=3.12
